bri_test_dtapi-1.0.2.dist-info/licenses/LICENSE
domaintools/__init__.py
domaintools/_version.py
domaintools/api.py
domaintools/base_results.py
domaintools/constants.py
domaintools/exceptions.py
domaintools/filters.py
domaintools/results.py
domaintools/utils.py
domaintools/cli/__init__.py
domaintools/cli/api.py
domaintools/cli/constants.py
domaintools/cli/main.py
domaintools/cli/utils.py
domaintools/cli/commands/__init__.py
domaintools/cli/commands/accounts.py
domaintools/cli/commands/detects.py
domaintools/cli/commands/domains.py
domaintools/cli/commands/feeds.py
domaintools/cli/commands/ips.py
domaintools/cli/commands/iris.py
domaintools/cli/commands/phisheye.py
domaintools_async/__init__.py
bri_test_dtapi-1.0.2.dist-info/METADATA
bri_test_dtapi-1.0.2.dist-info/WHEEL
bri_test_dtapi-1.0.2.dist-info/entry_points.txt
bri_test_dtapi-1.0.2.dist-info/top_level.txt
bri_test_dtapi-1.0.2.dist-info/RECORD
